canano/__init__.py
canano/canano.py
canano-0.0.4.dist-info/LICENSE
canano-0.0.4.dist-info/METADATA
canano-0.0.4.dist-info/WHEEL
canano-0.0.4.dist-info/top_level.txt
canano-0.0.4.dist-info/RECORD
