Metadata-Version: 2.1
Name: canano
Version: 0.0.4
Summary: Python library for Canano Raspberry Pi add-on board
Home-page: https://github.com/Tbruno25/canano
Author: Tj Bruno
Author-email: Tbruno25@gmail.com
License: UNKNOWN
Platform: UNKNOWN
Requires-Dist: aenum (==2.2.3)
Requires-Dist: in-place (==0.4.0)
Requires-Dist: python-can (==3.3.2)
Requires-Dist: RPi.GPIO (==0.7.0)
Requires-Dist: wrapt (==1.12.1)
Requires-Dist: pysocketcan (==0.0.2)
